rss_da_stac/__init__.py
rss_da_stac/_version.py
rss_da_stac/cli.py
rss_da_stac/uri2l2a.py
rss_da_stac/utils.py
rss_da_stac-0.1.0.dist-info/METADATA
rss_da_stac-0.1.0.dist-info/WHEEL
rss_da_stac-0.1.0.dist-info/entry_points.txt
rss_da_stac-0.1.0.dist-info/licenses/LICENSE
rss_da_stac-0.1.0.dist-info/RECORD
