Metadata-Version: 2.4
Name: rss_da_stac
Version: 0.1.0
Summary: Utilities for JRSRP users to interact with common STAC providers
Author-email: rdenham <robert.denham@detsi.qld.gov.au>
License-File: LICENSE
Requires-Python: >=3.11
Requires-Dist: planetary-computer>=1.0.0
Requires-Dist: pystac-client<0.10.0
Requires-Dist: pystac>=1.13.0
Requires-Dist: pytz>=2025.2
Requires-Dist: tifftools>=1.6.1
Requires-Dist: typer>=0.16.0
